llama_index/tools/wolfram_alpha/__init__.py
llama_index/tools/wolfram_alpha/base.py
llama_index_tools_wolfram_alpha-0.5.0.dist-info/METADATA
llama_index_tools_wolfram_alpha-0.5.0.dist-info/WHEEL
llama_index_tools_wolfram_alpha-0.5.0.dist-info/licenses/LICENSE
llama_index_tools_wolfram_alpha-0.5.0.dist-info/RECORD
